randfunc/RANDFUNC.py
randfunc/__init__.py
randfunc-0.0.4.dist-info/LICENSE
randfunc-0.0.4.dist-info/METADATA
randfunc-0.0.4.dist-info/WHEEL
randfunc-0.0.4.dist-info/top_level.txt
randfunc-0.0.4.dist-info/RECORD
