Metadata-Version: 2.1
Name: randfunc
Version: 0.0.4
Summary: A package full of random functions...
Home-page: https://github.com/Cu3t0m/randfunc
Author: Diwan Mohamed Faheer
Author-email: diwanmohamedfaheer@gmail.com
License: UNKNOWN
Platform: UNKNOWN
Classifier: Programming Language :: Python :: 3
Classifier: License :: OSI Approved :: MIT License
Classifier: Operating System :: OS Independent
Requires-Dist: art (==5.3)
Requires-Dist: instant-api-client (==0.1.2)
